{
  "year": 2015,
  "season": "summer",
  "entries": [
    {
      "mikan_id": "528",
      "bgmtv_id": 126024,
      "title_chinese": "创圣的大天使LOGOS",
      "title_japanese": "アクエリオンロゴス",
      "air_week": 4,
      "poster_url": "https://lain.bgm.tv/pic/cover/l/75/27/126024_uGE8A.jpg",
      "year": 2015,
      "platform": "tv",
      "total_episodes": 26,
      "air_date": "2015-07-02"
    },
    {
      "mikan_id": "229",
      "bgmtv_id": 2782,
      "title_chinese": "火影忍者疾风传",
      "title_japanese": "NARUTO -ナルト- 疾風伝",
      "air_week": 4,
      "poster_url": "https://lain.bgm.tv/pic/cover/l/60/24/2782_z3jWE.jpg",
      "year": 2007,
      "platform": "tv",
      "total_episodes": 500,
      "air_date": "2007-02-15"
    },
    {
      "mikan_id": "532",
      "bgmtv_id": 120369,
      "title_chinese": "黑塔利亚 第6期",
      "title_japanese": "ヘタリア The World Twinkle",
      "air_week": 5,
      "poster_url": "https://lain.bgm.tv/pic/cover/l/bd/85/120369_gdGxh.jpg",
      "year": 2015,
      "platform": "tv",
      "total_episodes": 18,
      "air_date": "2015-07-03"
    },
    {
      "mikan_id": "529",
      "bgmtv_id": 118785,
      "title_chinese": "乱步奇谭 拉普拉斯的游戏",
      "title_japanese": "乱歩奇譚 Game of Laplace",
      "air_week": 4,
      "poster_url": "https://lain.bgm.tv/pic/cover/l/c4/2d/118785_RrA1D.jpg",
      "year": 2015,
      "platform": "tv",
      "total_episodes": 11,
      "air_date": "2015-07-02"
    },
    {
      "mikan_id": "382",
      "bgmtv_id": 139318,
      "title_chinese": "偶像活动 第三年",
      "title_japanese": "アイカツ!3年目",
      "air_week": 4,
      "poster_url": "https://lain.bgm.tv/pic/cover/l/fc/10/139318_vW7q2.jpg",
      "year": 2014,
      "platform": "tv",
      "total_episodes": 51,
      "air_date": "2014-10-02"
    },
    {
      "mikan_id": "530",
      "bgmtv_id": 126779,
      "title_chinese": "青春×机关枪",
      "title_japanese": "青春×機関銃",
      "air_week": 4,
      "poster_url": "https://lain.bgm.tv/pic/cover/l/b1/7b/126779_R73wU.jpg",
      "year": 2015,
      "platform": "tv",
      "total_episodes": 13,
      "air_date": "2015-07-02"
    },
    {
      "mikan_id": "531",
      "bgmtv_id": 117556,
      "title_chinese": "城下町的蒲公英",
      "title_japanese": "城下町のダンデライオン",
      "air_week": 4,
      "poster_url": "https://lain.bgm.tv/pic/cover/l/e4/00/117556_A0YTI.jpg",
      "year": 2015,
      "platform": "tv",
      "total_episodes": 12,
      "air_date": "2015-07-02"
    },
    {
      "mikan_id": "533",
      "bgmtv_id": 124185,
      "title_chinese": "潮与虎",
      "title_japanese": "うしおととら",
      "air_week": 5,
      "poster_url": "https://lain.bgm.tv/pic/cover/l/a1/d9/124185_kOXYX.jpg",
      "year": 2015,
      "platform": "tv",
      "total_episodes": 26,
      "air_date": "2015-07-03"
    },
    {
      "mikan_id": "527",
      "bgmtv_id": 125917,
      "title_chinese": "Chaos Dragon 赤龙战役",
      "title_japanese": "ケイオスドラゴン 赤竜戦役",
      "air_week": 4,
      "poster_url": "https://lain.bgm.tv/pic/cover/l/bc/29/125917_ZZG1w.jpg",
      "year": 2015,
      "platform": "tv",
      "total_episodes": 12,
      "air_date": "2015-07-02"
    },
    {
      "mikan_id": "479",
      "bgmtv_id": 90815,
      "title_chinese": "长门有希酱的消失",
      "title_japanese": "長門有希ちゃんの消失",
      "air_week": 5,
      "poster_url": "https://lain.bgm.tv/pic/cover/l/f1/20/90815_4s8XP.jpg",
      "year": 2015,
      "platform": "tv",
      "total_episodes": 16,
      "air_date": "2015-04-03"
    },
    {
      "mikan_id": "566",
      "bgmtv_id": 106693,
      "title_chinese": "学园孤岛",
      "title_japanese": "がっこうぐらし！",
      "air_week": 4,
      "poster_url": "https://lain.bgm.tv/pic/cover/l/e9/a7/106693_68MDM.jpg",
      "year": 2015,
      "platform": "tv",
      "total_episodes": 12,
      "air_date": "2015-07-09"
    },
    {
      "mikan_id": "481",
      "bgmtv_id": 116461,
      "title_chinese": "食戟之灵",
      "title_japanese": "食戟のソーマ",
      "air_week": 5,
      "poster_url": "https://lain.bgm.tv/pic/cover/l/96/99/116461_zl6M2.jpg",
      "year": 2015,
      "platform": "tv",
      "total_episodes": 33,
      "air_date": "2015-04-03"
    },
    {
      "mikan_id": "534",
      "bgmtv_id": 129105,
      "title_chinese": "黑白小姐 第二季",
      "title_japanese": "ミス・モノクローム -The Animation- 2",
      "air_week": 5,
      "poster_url": "https://lain.bgm.tv/pic/cover/l/2d/34/129105_uFMGf.jpg",
      "year": 2015,
      "platform": "tv",
      "total_episodes": 13,
      "air_date": "2015-07-03"
    },
    {
      "mikan_id": "571",
      "bgmtv_id": 130231,
      "title_chinese": "偶像大师 灰姑娘女孩 第二季",
      "title_japanese": "アイドルマスター シンデレラガールズ 2ndシーズン",
      "air_week": 5,
      "poster_url": "https://lain.bgm.tv/pic/cover/l/6d/a9/130231_YPZJn.jpg",
      "year": 2015,
      "platform": "tv",
      "total_episodes": 15,
      "air_date": "2015-07-17"
    },
    {
      "mikan_id": "538",
      "bgmtv_id": 129087,
      "title_chinese": "教室☆危机",
      "title_japanese": "Classroom☆Crisis",
      "air_week": 5,
      "poster_url": "https://lain.bgm.tv/pic/cover/l/e3/97/129087_3XC7m.jpg",
      "year": 2015,
      "platform": "tv",
      "total_episodes": 14,
      "air_date": "2015-07-03"
    },
    {
      "mikan_id": "535",
      "bgmtv_id": 121003,
      "title_chinese": "兔宝的悲惨日常 梦幻篇",
      "title_japanese": "うーさーのその日暮らし 夢幻編",
      "air_week": 5,
      "poster_url": "https://lain.bgm.tv/pic/cover/l/c8/5f/121003_X6G3K.jpg",
      "year": 2015,
      "platform": "tv",
      "total_episodes": 13,
      "air_date": "2015-07-03"
    },
    {
      "mikan_id": "537",
      "bgmtv_id": 120445,
      "title_chinese": "GATE 奇幻自卫队",
      "title_japanese": "GATE 自衛隊 彼の地にて、斯く戦えり",
      "air_week": 5,
      "poster_url": "https://lain.bgm.tv/pic/cover/l/a0/d0/120445_8e63L.jpg",
      "year": 2015,
      "platform": "tv",
      "total_episodes": 12,
      "air_date": "2015-07-03"
    },
    {
      "mikan_id": "539",
      "bgmtv_id": 90512,
      "title_chinese": "战姬绝唱SYMPHOGEAR GX",
      "title_japanese": "戦姫絶唱シンフォギアGX",
      "air_week": 5,
      "poster_url": "https://lain.bgm.tv/pic/cover/l/0b/e4/90512_D8mqk.jpg",
      "year": 2015,
      "platform": "tv",
      "total_episodes": 17,
      "air_date": "2015-07-03"
    },
    {
      "mikan_id": "536",
      "bgmtv_id": 128635,
      "title_chinese": "若叶女孩",
      "title_japanese": "わかば＊ガール",
      "air_week": 5,
      "poster_url": "https://lain.bgm.tv/pic/cover/l/6c/29/128635_QNdI0.jpg",
      "year": 2015,
      "platform": "tv",
      "total_episodes": 14,
      "air_date": "2015-07-03"
    },
    {
      "mikan_id": "483",
      "bgmtv_id": 120186,
      "title_chinese": "美妙天堂 第二期",
      "title_japanese": "プリパラ 2nd season",
      "air_week": 6,
      "poster_url": "https://lain.bgm.tv/pic/cover/l/07/72/120186_u0051.jpg",
      "year": 2015,
      "platform": "tv",
      "total_episodes": 51,
      "air_date": "2015-04-04"
    },
    {
      "mikan_id": "323",
      "bgmtv_id": 91946,
      "title_chinese": "妖精的尾巴 第二季",
      "title_japanese": "FAIRY TAIL 第2期",
      "air_week": 6,
      "poster_url": "https://lain.bgm.tv/pic/cover/l/65/f5/91946_qTQpV.jpg",
      "year": 2014,
      "platform": "tv",
      "total_episodes": 102,
      "air_date": "2014-04-05"
    },
    {
      "mikan_id": "482",
      "bgmtv_id": 129823,
      "title_chinese": "宝石宠物 Magical Change",
      "title_japanese": "ジュエルペット マジカルチェンジ",
      "air_week": 6,
      "poster_url": "https://lain.bgm.tv/pic/cover/l/c1/f8/129823_66bp4.jpg",
      "year": 2015,
      "platform": "tv",
      "total_episodes": 39,
      "air_date": "2015-04-04"
    },
    {
      "mikan_id": "681",
      "bgmtv_id": 18692,
      "title_chinese": "哆啦A梦",
      "title_japanese": "ドラえもん",
      "air_week": 5,
      "poster_url": "https://lain.bgm.tv/pic/cover/l/b4/4f/18692_Gilpl.jpg",
      "year": 2005,
      "platform": "tv",
      "total_episodes": 913,
      "air_date": "2005-04-15"
    },
    {
      "mikan_id": "568",
      "bgmtv_id": 110048,
      "title_chinese": "监狱学园",
      "title_japanese": "監獄学園",
      "air_week": 5,
      "poster_url": "https://lain.bgm.tv/pic/cover/l/1c/0b/110048_JHz0j.jpg",
      "year": 2015,
      "platform": "tv",
      "total_episodes": 12,
      "air_date": "2015-07-10"
    },
    {
      "mikan_id": "572",
      "bgmtv_id": 113134,
      "title_chinese": "Fate/kaleid liner 魔法少女☆伊莉雅 2wei Herz!",
      "title_japanese": "Fate/kaleid liner プリズマ☆イリヤ ツヴァイヘルツ!",
      "air_week": 5,
      "poster_url": "https://lain.bgm.tv/pic/cover/l/0f/31/113134_NkaCg.jpg",
      "year": 2015,
      "platform": "tv",
      "total_episodes": 15,
      "air_date": "2015-07-24"
    },
    {
      "mikan_id": "567",
      "bgmtv_id": 125896,
      "title_chinese": "群居姐妹",
      "title_japanese": "だんちがい",
      "air_week": 4,
      "poster_url": "https://lain.bgm.tv/pic/cover/l/91/1d/125896_iKAVv.jpg",
      "year": 2015,
      "platform": "tv",
      "total_episodes": 13,
      "air_date": "2015-07-09"
    },
    {
      "mikan_id": "208",
      "bgmtv_id": 78799,
      "title_chinese": "精灵宝可梦XY",
      "title_japanese": "ポケットモンスターXY",
      "air_week": 0,
      "poster_url": "https://lain.bgm.tv/pic/cover/l/ca/e3/78799_f9bqW.jpg",
      "year": 2013,
      "platform": "tv",
      "total_episodes": 93,
      "air_date": "2013-10-17"
    },
    {
      "mikan_id": "519",
      "bgmtv_id": 116716,
      "title_chinese": "圣斗士星矢 黄金魂 -soul of gold-",
      "title_japanese": "聖闘士星矢 黄金魂 -soul of gold-",
      "air_week": 6,
      "poster_url": "https://lain.bgm.tv/pic/cover/l/e2/27/116716_2yMIL.jpg",
      "year": 2015,
      "platform": "tv",
      "total_episodes": 13,
      "air_date": "2015-04-11"
    },
    {
      "mikan_id": "493",
      "bgmtv_id": 105075,
      "title_chinese": "血界战线",
      "title_japanese": "血界戦線",
      "air_week": 6,
      "poster_url": "https://lain.bgm.tv/pic/cover/l/f9/2c/105075_iNy58.jpg",
      "year": 2015,
      "platform": "tv",
      "total_episodes": 14,
      "air_date": "2015-04-04"
    },
    {
      "mikan_id": "484",
      "bgmtv_id": 122606,
      "title_chinese": "电波教师",
      "title_japanese": "電波教師",
      "air_week": 6,
      "poster_url": "https://lain.bgm.tv/pic/cover/l/24/c0/122606_77iwf.jpg",
      "year": 2015,
      "platform": "tv",
      "total_episodes": 24,
      "air_date": "2015-04-04"
    },
    {
      "mikan_id": "485",
      "bgmtv_id": 117731,
      "title_chinese": "境界的轮回",
      "title_japanese": "境界のRINNE",
      "air_week": 6,
      "poster_url": "https://lain.bgm.tv/pic/cover/l/7c/2e/117731_I9PEm.jpg",
      "year": 2015,
      "platform": "tv",
      "total_episodes": 25,
      "air_date": "2015-04-04"
    },
    {
      "mikan_id": "541",
      "bgmtv_id": 120925,
      "title_chinese": "夏洛特",
      "title_japanese": "Charlotte",
      "air_week": 6,
      "poster_url": "https://lain.bgm.tv/pic/cover/l/9b/d6/120925_Zp040.jpg",
      "year": 2015,
      "platform": "tv",
      "total_episodes": 15,
      "air_date": "2015-07-04"
    },
    {
      "mikan_id": "543",
      "bgmtv_id": 115780,
      "title_chinese": "没有黄段子存在的无聊世界",
      "title_japanese": "下ネタという概念が存在しない退屈な世界",
      "air_week": 6,
      "poster_url": "https://lain.bgm.tv/pic/cover/l/13/84/115780_TDTJi.jpg",
      "year": 2015,
      "platform": "tv",
      "total_episodes": 13,
      "air_date": "2015-07-04"
    },
    {
      "mikan_id": "465",
      "bgmtv_id": 119279,
      "title_chinese": "Go! Princess 光之美少女",
      "title_japanese": "Go! プリンセスプリキュア",
      "air_week": 0,
      "poster_url": "https://lain.bgm.tv/pic/cover/l/f5/72/119279_5v8yG.jpg",
      "year": 2015,
      "platform": "tv",
      "total_episodes": 50,
      "air_date": "2015-02-01"
    },
    {
      "mikan_id": "279",
      "bgmtv_id": 92161,
      "title_chinese": "游戏王ARC-V",
      "title_japanese": "遊☆戯☆王ARC-V",
      "air_week": 0,
      "poster_url": "https://lain.bgm.tv/pic/cover/l/c1/75/92161_R2GYo.jpg",
      "year": 2014,
      "platform": "tv",
      "total_episodes": 148,
      "air_date": "2014-04-06"
    },
    {
      "mikan_id": "227",
      "bgmtv_id": 899,
      "title_chinese": "名侦探柯南",
      "title_japanese": "名探偵コナン",
      "air_week": 0,
      "poster_url": "https://lain.bgm.tv/pic/cover/l/01/88/899_REwVW.jpg",
      "year": 1996,
      "platform": "tv",
      "total_episodes": 1308,
      "air_date": "1996-01-08"
    },
    {
      "mikan_id": "540",
      "bgmtv_id": 114967,
      "title_chinese": "无头骑士异闻录×2 转",
      "title_japanese": "デュラララ!!×2 転",
      "air_week": 6,
      "poster_url": "https://lain.bgm.tv/pic/cover/l/53/ef/114967_U49lI.jpg",
      "year": 2015,
      "platform": "tv",
      "total_episodes": 12,
      "air_date": "2015-07-04"
    },
    {
      "mikan_id": "228",
      "bgmtv_id": 975,
      "title_chinese": "航海王",
      "title_japanese": "ONE PIECE",
      "air_week": 0,
      "poster_url": "https://lain.bgm.tv/pic/cover/l/92/97/975_YKuWd.jpg",
      "year": 1999,
      "platform": "tv",
      "total_episodes": 1191,
      "air_date": "1999-10-20"
    },
    {
      "mikan_id": "412",
      "bgmtv_id": 104906,
      "title_chinese": "境界触发者",
      "title_japanese": "ワールドトリガー",
      "air_week": 0,
      "poster_url": "https://lain.bgm.tv/pic/cover/l/a4/d7/104906_2noZn.jpg",
      "year": 2014,
      "platform": "tv",
      "total_episodes": 73,
      "air_date": "2014-10-05"
    },
    {
      "mikan_id": "542",
      "bgmtv_id": 110648,
      "title_chinese": "迷糊餐厅 第三季",
      "title_japanese": "WORKING!!!",
      "air_week": 6,
      "poster_url": "https://lain.bgm.tv/pic/cover/l/59/dc/110648_52R1q.jpg",
      "year": 2015,
      "platform": "tv",
      "total_episodes": 14,
      "air_date": "2015-07-04"
    },
    {
      "mikan_id": "546",
      "bgmtv_id": 118067,
      "title_chinese": "六花的勇者",
      "title_japanese": "六花の勇者",
      "air_week": 6,
      "poster_url": "https://lain.bgm.tv/pic/cover/l/72/41/118067_1O0l2.jpg",
      "year": 2015,
      "platform": "tv",
      "total_episodes": 12,
      "air_date": "2015-07-04"
    },
    {
      "mikan_id": "501",
      "bgmtv_id": 129844,
      "title_chinese": "钻石王牌 第二季",
      "title_japanese": "ダイヤのA -SECOND SEASON-",
      "air_week": 1,
      "poster_url": "https://lain.bgm.tv/pic/cover/l/1c/90/129844_NwzEg.jpg",
      "year": 2015,
      "platform": "tv",
      "total_episodes": 51,
      "air_date": "2015-04-06"
    },
    {
      "mikan_id": "552",
      "bgmtv_id": 120763,
      "title_chinese": "出包王女Darkness 第二季",
      "title_japanese": "To LOVEる -とらぶる- ダークネス 2nd",
      "air_week": 0,
      "poster_url": "https://lain.bgm.tv/pic/cover/l/38/c9/120763_Tz4Xl.jpg",
      "year": 2015,
      "platform": "tv",
      "total_episodes": 15,
      "air_date": "2015-07-06"
    },
    {
      "mikan_id": "549",
      "bgmtv_id": 113629,
      "title_chinese": "噬神者",
      "title_japanese": "GOD EATER",
      "air_week": 0,
      "poster_url": "https://lain.bgm.tv/pic/cover/l/e8/dc/113629_aafNG.jpg",
      "year": 2015,
      "platform": "tv",
      "total_episodes": 17,
      "air_date": "2015-07-12"
    },
    {
      "mikan_id": "545",
      "bgmtv_id": 86721,
      "title_chinese": "科学小飞侠Crowds insight",
      "title_japanese": "ガッチャマン クラウズ インサイト",
      "air_week": 0,
      "poster_url": "https://lain.bgm.tv/pic/cover/l/ac/0b/86721_rBK9h.jpg",
      "year": 2015,
      "platform": "tv",
      "total_episodes": 13,
      "air_date": "2015-07-05"
    },
    {
      "mikan_id": "495",
      "bgmtv_id": 116871,
      "title_chinese": "亚尔斯兰战记",
      "title_japanese": "アルスラーン戦記",
      "air_week": 0,
      "poster_url": "https://lain.bgm.tv/pic/cover/l/9b/bf/116871_TEaP5.jpg",
      "year": 2015,
      "platform": "tv",
      "total_episodes": 26,
      "air_date": "2015-04-05"
    },
    {
      "mikan_id": "548",
      "bgmtv_id": 129384,
      "title_chinese": "和歌子酒",
      "title_japanese": "ワカコ酒",
      "air_week": 0,
      "poster_url": "https://lain.bgm.tv/pic/cover/l/74/4d/129384_vd3ir.jpg",
      "year": 2015,
      "platform": "tv",
      "total_episodes": 12,
      "air_date": "2015-07-05"
    },
    {
      "mikan_id": "569",
      "bgmtv_id": 127294,
      "title_chinese": "维纳斯计划 CLIMAX",
      "title_japanese": "VENUS PROJECT -CLIMAX-",
      "air_week": 0,
      "poster_url": "https://lain.bgm.tv/pic/cover/l/cf/19/127294_iM1U1.jpg",
      "year": 2015,
      "platform": "tv",
      "total_episodes": 12,
      "air_date": "2015-07-12"
    },
    {
      "mikan_id": "496",
      "bgmtv_id": 113906,
      "title_chinese": "网球优等生 第二季",
      "title_japanese": "ベイビーステップ 第2シリーズ",
      "air_week": 0,
      "poster_url": "https://lain.bgm.tv/pic/cover/l/40/83/113906_NO75R.jpg",
      "year": 2015,
      "platform": "tv",
      "total_episodes": 25,
      "air_date": "2015-04-05"
    },
    {
      "mikan_id": "553",
      "bgmtv_id": 130452,
      "title_chinese": "网球并不可笑嘛 5期",
      "title_japanese": "てーきゅう 5期",
      "air_week": 1,
      "poster_url": "https://lain.bgm.tv/pic/cover/l/c5/9c/130452_0w2FT.jpg",
      "year": 2015,
      "platform": "tv",
      "total_episodes": 14,
      "air_date": "2015-07-06"
    },
    {
      "mikan_id": "555",
      "bgmtv_id": 101442,
      "title_chinese": "悠哉日常大王 Repeat",
      "title_japanese": "のんのんびより  りぴーと",
      "air_week": 1,
      "poster_url": "https://lain.bgm.tv/pic/cover/l/8b/6b/101442_EM1Vg.jpg",
      "year": 2015,
      "platform": "tv",
      "total_episodes": 12,
      "air_date": "2015-07-06"
    },
    {
      "mikan_id": "551",
      "bgmtv_id": 126034,
      "title_chinese": "赤发白雪姬",
      "title_japanese": "赤髪の白雪姫",
      "air_week": 1,
      "poster_url": "https://lain.bgm.tv/pic/cover/l/7d/82/126034_zXVXx.jpg",
      "year": 2015,
      "platform": "tv",
      "total_episodes": 12,
      "air_date": "2015-07-06"
    },
    {
      "mikan_id": "570",
      "bgmtv_id": 132829,
      "title_chinese": "枕男子",
      "title_japanese": "枕男子",
      "air_week": 1,
      "poster_url": "https://lain.bgm.tv/pic/cover/l/f3/d5/132829_M4Mb7.jpg",
      "year": 2015,
      "platform": "tv",
      "total_episodes": 13,
      "air_date": "2015-07-13"
    },
    {
      "mikan_id": "554",
      "bgmtv_id": 123539,
      "title_chinese": "其实我是",
      "title_japanese": "実は私は",
      "air_week": 1,
      "poster_url": "https://lain.bgm.tv/pic/cover/l/3e/42/123539_LBfl6.jpg",
      "year": 2015,
      "platform": "tv",
      "total_episodes": 13,
      "air_date": "2015-07-06"
    },
    {
      "mikan_id": "557",
      "bgmtv_id": 133962,
      "title_chinese": "怪兽酒场干杯！",
      "title_japanese": "怪獣酒場カンパーイ！",
      "air_week": 2,
      "poster_url": "https://lain.bgm.tv/pic/cover/l/6f/9c/133962_n909h.jpg",
      "year": 2015,
      "platform": "tv",
      "total_episodes": 26,
      "air_date": "2015-07-07"
    },
    {
      "mikan_id": "559",
      "bgmtv_id": 121377,
      "title_chinese": "那就是声优！",
      "title_japanese": "それが声優！",
      "air_week": 2,
      "poster_url": "https://lain.bgm.tv/pic/cover/l/c4/5a/121377_58QQ3.jpg",
      "year": 2015,
      "platform": "tv",
      "total_episodes": 17,
      "air_date": "2015-07-07"
    },
    {
      "mikan_id": "558",
      "bgmtv_id": 112146,
      "title_chinese": "OVERLORD",
      "title_japanese": "オーバーロード",
      "air_week": 2,
      "poster_url": "https://lain.bgm.tv/pic/cover/l/cd/a9/112146_qr9m3.jpg",
      "year": 2015,
      "platform": "tv",
      "total_episodes": 13,
      "air_date": "2015-07-07"
    },
    {
      "mikan_id": "560",
      "bgmtv_id": 127979,
      "title_chinese": "魔物娘的同居日常",
      "title_japanese": "モンスター娘のいる日常",
      "air_week": 2,
      "poster_url": "https://lain.bgm.tv/pic/cover/l/fd/f5/127979_BSR5R.jpg",
      "year": 2015,
      "platform": "tv",
      "total_episodes": 12,
      "air_date": "2015-07-07"
    },
    {
      "mikan_id": "509",
      "bgmtv_id": 120791,
      "title_chinese": "银魂°",
      "title_japanese": "銀魂°",
      "air_week": 3,
      "poster_url": "https://lain.bgm.tv/pic/cover/l/92/f6/120791_0Sfdz.jpg",
      "year": 2015,
      "platform": "tv",
      "total_episodes": 51,
      "air_date": "2015-04-08"
    },
    {
      "mikan_id": "556",
      "bgmtv_id": 124615,
      "title_chinese": "百万偶像",
      "title_japanese": "ミリオンドール",
      "air_week": 1,
      "poster_url": "https://lain.bgm.tv/pic/cover/l/e6/ea/124615_DpPD4.jpg",
      "year": 2015,
      "platform": "tv",
      "total_episodes": 12,
      "air_date": "2015-07-06"
    },
    {
      "mikan_id": "561",
      "bgmtv_id": 134038,
      "title_chinese": "比基尼勇士",
      "title_japanese": "BIKINI WARRIORS",
      "air_week": 2,
      "poster_url": "https://lain.bgm.tv/pic/cover/l/c7/5e/134038_VyuJ5.jpg",
      "year": 2015,
      "platform": "tv",
      "total_episodes": 13,
      "air_date": "2015-07-07"
    },
    {
      "mikan_id": "522",
      "bgmtv_id": 125624,
      "title_chinese": "英国一家，吃在日本",
      "title_japanese": "英国一家、日本を食べる",
      "air_week": 3,
      "poster_url": "https://lain.bgm.tv/pic/cover/l/f8/7c/125624_GITjZ.jpg",
      "year": 2015,
      "platform": "tv",
      "total_episodes": 24,
      "air_date": "2015-04-15"
    },
    {
      "mikan_id": "562",
      "bgmtv_id": 135202,
      "title_chinese": "洲崎西 THE ANIMATION",
      "title_japanese": "洲崎西 THE ANIMATION",
      "air_week": 3,
      "poster_url": "https://lain.bgm.tv/pic/cover/l/9c/09/135202_WD73p.jpg",
      "year": 2015,
      "platform": "tv",
      "total_episodes": 12,
      "air_date": "2015-07-08"
    },
    {
      "mikan_id": "511",
      "bgmtv_id": 117153,
      "title_chinese": "俺物语!!",
      "title_japanese": "俺物語!!",
      "air_week": 3,
      "poster_url": "https://lain.bgm.tv/pic/cover/l/85/68/117153_Zg4g8.jpg",
      "year": 2015,
      "platform": "tv",
      "total_episodes": 24,
      "air_date": "2015-04-08"
    },
    {
      "mikan_id": "525",
      "bgmtv_id": 119889,
      "title_chinese": "我老婆是学生会长",
      "title_japanese": "おくさまが生徒会長!",
      "air_week": 3,
      "poster_url": "https://lain.bgm.tv/pic/cover/l/c3/49/119889_191zj.jpg",
      "year": 2015,
      "platform": "tv",
      "total_episodes": 12,
      "air_date": "2015-07-01"
    },
    {
      "mikan_id": "565",
      "bgmtv_id": 120187,
      "title_chinese": "干物妹！小埋",
      "title_japanese": "干物妹! うまるちゃん",
      "air_week": 3,
      "poster_url": "https://lain.bgm.tv/pic/cover/l/41/2c/120187_nXjYb.jpg",
      "year": 2015,
      "platform": "tv",
      "total_episodes": 24,
      "air_date": "2015-07-08"
    },
    {
      "mikan_id": "564",
      "bgmtv_id": 109541,
      "title_chinese": "纯情罗曼史3",
      "title_japanese": "純情ロマンチカ3",
      "air_week": 3,
      "poster_url": "https://lain.bgm.tv/pic/cover/l/d4/9d/109541_0g022.jpg",
      "year": 2015,
      "platform": "tv",
      "total_episodes": 12,
      "air_date": "2015-07-08"
    },
    {
      "mikan_id": "526",
      "bgmtv_id": 107957,
      "title_chinese": "黑街匪徒",
      "title_japanese": "ギャングスタ",
      "air_week": 3,
      "poster_url": "https://lain.bgm.tv/pic/cover/l/d5/b2/107957_U9rbN.jpg",
      "year": 2015,
      "platform": "tv",
      "total_episodes": 13,
      "air_date": "2015-07-01"
    },
    {
      "mikan_id": "563",
      "bgmtv_id": 108377,
      "title_chinese": "空战魔导士候补生的教官",
      "title_japanese": "空戦魔導士候補生の教官",
      "air_week": 3,
      "poster_url": "https://lain.bgm.tv/pic/cover/l/4e/a9/108377_523z5.jpg",
      "year": 2015,
      "platform": "tv",
      "total_episodes": 12,
      "air_date": "2015-07-08"
    }
  ]
}