{
  "year": 2024,
  "season": "summer",
  "entries": [
    {
      "mikan_id": "3015",
      "bgmtv_id": 411247,
      "tmdb_id": null,
      "title_chinese": "宝可梦 地平线",
      "title_japanese": "ポケットモンスター",
      "season": 1,
      "year": 2023,
      "platform": "tv",
      "total_episodes": 126,
      "poster_url": "https://lain.bgm.tv/pic/cover/l/12/1b/411247_2bMzX.jpg",
      "air_date": "2023-04-14",
      "air_week": 5
    },
    {
      "mikan_id": "3288",
      "bgmtv_id": 354700,
      "tmdb_id": null,
      "title_chinese": "吉伊卡哇",
      "title_japanese": "ちいかわ",
      "season": 1,
      "year": 2022,
      "platform": "tv",
      "total_episodes": 257,
      "poster_url": "https://lain.bgm.tv/pic/cover/l/c9/b1/354700_S6YP6.jpg",
      "air_date": "2022-04-04",
      "air_week": 5
    },
    {
      "mikan_id": "681",
      "bgmtv_id": 18692,
      "tmdb_id": null,
      "title_chinese": "哆啦A梦",
      "title_japanese": "ドラえもん",
      "season": 1,
      "year": 2005,
      "platform": "tv",
      "total_episodes": 913,
      "poster_url": "https://lain.bgm.tv/pic/cover/l/b4/4f/18692_Gilpl.jpg",
      "air_date": "2005-04-15",
      "air_week": 5
    },
    {
      "mikan_id": "3394",
      "bgmtv_id": 410346,
      "tmdb_id": null,
      "title_chinese": "2.5次元的诱惑",
      "title_japanese": "2.5次元の誘惑",
      "season": 1,
      "year": 2024,
      "platform": "tv",
      "total_episodes": 24,
      "poster_url": "https://lain.bgm.tv/pic/cover/l/53/13/410346_MmQCm.jpg",
      "air_date": "2024-07-05",
      "air_week": 5
    },
    {
      "mikan_id": "3370",
      "bgmtv_id": 450586,
      "tmdb_id": null,
      "title_chinese": "地下城里的人们",
      "title_japanese": "ダンジョンの中のひと",
      "season": 1,
      "year": 2024,
      "platform": "tv",
      "total_episodes": 12,
      "poster_url": "https://lain.bgm.tv/pic/cover/l/32/fd/450586_E67D6.jpg",
      "air_date": "2024-07-05",
      "air_week": 5
    },
    {
      "mikan_id": "3374",
      "bgmtv_id": 425890,
      "tmdb_id": null,
      "title_chinese": "这个世界漏洞百出",
      "title_japanese": "この世界は不完全すぎる",
      "season": 1,
      "year": 2024,
      "platform": "tv",
      "total_episodes": 13,
      "poster_url": "https://lain.bgm.tv/pic/cover/l/97/5c/425890_4dXnI.jpg",
      "air_date": "2024-07-05",
      "air_week": 5
    },
    {
      "mikan_id": "3385",
      "bgmtv_id": 448613,
      "tmdb_id": null,
      "title_chinese": "古连泰沙U",
      "title_japanese": "グレンダイザーU",
      "season": 1,
      "year": 2024,
      "platform": "tv",
      "total_episodes": 13,
      "poster_url": "https://lain.bgm.tv/pic/cover/l/42/88/448613_kxxk0.jpg",
      "air_date": "2024-07-05",
      "air_week": 5
    },
    {
      "mikan_id": "3356",
      "bgmtv_id": 491923,
      "tmdb_id": null,
      "title_chinese": "棉花糖女孩遇上闷骚男孩",
      "title_japanese": "まぁるい彼女と残念な彼氏",
      "season": 1,
      "year": 2024,
      "platform": "tv",
      "total_episodes": 6,
      "poster_url": "https://lain.bgm.tv/pic/cover/l/3c/d6/491923_jLP3j.jpg",
      "air_date": "2024-06-07",
      "air_week": 5
    },
    {
      "mikan_id": "3355",
      "bgmtv_id": 444046,
      "tmdb_id": null,
      "title_chinese": "异世界自杀小队",
      "title_japanese": "異世界スーサイド・スクワッド",
      "season": 1,
      "year": 2024,
      "platform": "tv",
      "total_episodes": 10,
      "poster_url": "https://lain.bgm.tv/pic/cover/l/00/ae/444046_9b5bM.jpg",
      "air_date": "2024-07-05",
      "air_week": 5
    },
    {
      "mikan_id": "3341",
      "bgmtv_id": 407573,
      "tmdb_id": null,
      "title_chinese": "关于我转生变成史莱姆这档事",
      "title_japanese": "転生したらスライムだった件",
      "season": 3,
      "year": 2024,
      "platform": "tv",
      "total_episodes": 26,
      "poster_url": "https://lain.bgm.tv/pic/cover/l/f0/f4/407573_993Vy.jpg",
      "air_date": "2024-04-05",
      "air_week": 5
    },
    {
      "mikan_id": "3397",
      "bgmtv_id": 499038,
      "tmdb_id": null,
      "title_chinese": "幽灵教授的恶女养成法则",
      "title_japanese": "未来の黒幕系悪役令嬢モリアーティーの異世界完全犯罪白書",
      "season": 1,
      "year": 2024,
      "platform": "tv",
      "total_episodes": 6,
      "poster_url": "https://lain.bgm.tv/pic/cover/l/db/9c/499038_i4g2e.jpg",
      "air_date": "2024-07-19",
      "air_week": 5
    },
    {
      "mikan_id": "3419",
      "bgmtv_id": 457991,
      "tmdb_id": null,
      "title_chinese": "到了联谊会上发现连一个女生都没有",
      "title_japanese": "合コンに行ったら女がいなかった話",
      "season": 1,
      "year": 2024,
      "platform": "tv",
      "total_episodes": 12,
      "poster_url": "https://lain.bgm.tv/pic/cover/l/97/ab/457991_FHbE4.jpg",
      "air_date": "2024-10-04",
      "air_week": 5
    },
    {
      "mikan_id": "3408",
      "bgmtv_id": 446618,
      "tmdb_id": null,
      "title_chinese": "尼尔：自动人形 Ver1.1a 第2部分",
      "title_japanese": "NieR:Automata Ver1.1a 第2クール",
      "season": 1,
      "year": 2024,
      "platform": "tv",
      "total_episodes": 13,
      "poster_url": "https://lain.bgm.tv/pic/cover/l/62/d8/446618_42Up5.jpg",
      "air_date": "2024-07-05",
      "air_week": 5
    },
    {
      "mikan_id": "3406",
      "bgmtv_id": 408195,
      "tmdb_id": null,
      "title_chinese": "再见，地球",
      "title_japanese": "ばいばい、アース",
      "season": 1,
      "year": 2024,
      "platform": "tv",
      "total_episodes": 10,
      "poster_url": "https://lain.bgm.tv/pic/cover/l/0d/8a/408195_I91PZ.jpg",
      "air_date": "2024-07-12",
      "air_week": 5
    },
    {
      "mikan_id": "3343",
      "bgmtv_id": 425587,
      "tmdb_id": null,
      "title_chinese": "我的英雄学院",
      "title_japanese": "僕のヒーローアカデミア",
      "season": 7,
      "year": 2024,
      "platform": "tv",
      "total_episodes": 21,
      "poster_url": "https://lain.bgm.tv/pic/cover/l/39/0b/425587_2U6Hh.jpg",
      "air_date": "2024-05-04",
      "air_week": 6
    },
    {
      "mikan_id": "3391",
      "bgmtv_id": 464376,
      "tmdb_id": null,
      "title_chinese": "败犬女主太多了！",
      "title_japanese": "負けヒロインが多すぎる！",
      "season": 1,
      "year": 2024,
      "platform": "tv",
      "total_episodes": 12,
      "poster_url": "https://lain.bgm.tv/pic/cover/l/e4/dc/464376_NsZRw.jpg",
      "air_date": "2024-07-13",
      "air_week": 6
    },
    {
      "mikan_id": "3327",
      "bgmtv_id": 444339,
      "tmdb_id": null,
      "title_chinese": "杀手寓言",
      "title_japanese": "ザ・ファブル",
      "season": 1,
      "year": 2024,
      "platform": "tv",
      "total_episodes": 25,
      "poster_url": "https://lain.bgm.tv/pic/cover/l/4c/ce/444339_2vcUB.jpg",
      "air_date": "2024-04-06",
      "air_week": 6
    },
    {
      "mikan_id": "3380",
      "bgmtv_id": 475354,
      "tmdb_id": null,
      "title_chinese": "物语系列 外传季&怪物季",
      "title_japanese": "〈物語〉シリーズ オフ&モンスターシーズン",
      "season": 1,
      "year": 2024,
      "platform": "tv",
      "total_episodes": 16,
      "poster_url": "https://lain.bgm.tv/pic/cover/l/85/c1/475354_QyO6r.jpg",
      "air_date": "2024-07-06",
      "air_week": 6
    },
    {
      "mikan_id": "3311",
      "bgmtv_id": 461338,
      "tmdb_id": null,
      "title_chinese": "乌鸦不择主",
      "title_japanese": "烏は主を選ばない",
      "season": 1,
      "year": 2024,
      "platform": "tv",
      "total_episodes": 21,
      "poster_url": "https://lain.bgm.tv/pic/cover/l/6b/ef/461338_mfpKk.jpg",
      "air_date": "2024-04-06",
      "air_week": 6
    },
    {
      "mikan_id": "3334",
      "bgmtv_id": 471769,
      "tmdb_id": null,
      "title_chinese": "影之诗F 方舟篇",
      "title_japanese": "シャドウバースF アーク編",
      "season": 1,
      "year": 2024,
      "platform": "tv",
      "total_episodes": 25,
      "poster_url": "https://lain.bgm.tv/pic/cover/l/c4/5a/471769_ojwc9.jpg",
      "air_date": "2024-04-13",
      "air_week": 6
    },
    {
      "mikan_id": "3369",
      "bgmtv_id": 478684,
      "tmdb_id": null,
      "title_chinese": "天穗之咲稻姬",
      "title_japanese": "天穂のサクナヒメ",
      "season": 1,
      "year": 2024,
      "platform": "tv",
      "total_episodes": 13,
      "poster_url": "https://lain.bgm.tv/pic/cover/l/e9/f4/478684_gVp0X.jpg",
      "air_date": "2024-07-06",
      "air_week": 6
    },
    {
      "mikan_id": "3365",
      "bgmtv_id": 472554,
      "tmdb_id": null,
      "title_chinese": "从路人角色开始的探索英雄谭",
      "title_japanese": "モブから始まる探索英雄譚",
      "season": 1,
      "year": 2024,
      "platform": "tv",
      "total_episodes": 12,
      "poster_url": "https://lain.bgm.tv/pic/cover/l/65/1c/472554_DZE6Z.jpg",
      "air_date": "2024-07-06",
      "air_week": 6
    },
    {
      "mikan_id": "3376",
      "bgmtv_id": 446615,
      "tmdb_id": null,
      "title_chinese": "为何我的世界被遗忘了？",
      "title_japanese": "なぜ僕の世界を誰も覚えていないのか？",
      "season": 1,
      "year": 2024,
      "platform": "tv",
      "total_episodes": 12,
      "poster_url": "https://lain.bgm.tv/pic/cover/l/b4/f9/446615_qpXQH.jpg",
      "air_date": "2024-07-13",
      "air_week": 6
    },
    {
      "mikan_id": "3377",
      "bgmtv_id": 475367,
      "tmdb_id": null,
      "title_chinese": "精灵小姐瘦不了。",
      "title_japanese": "エルフさんは痩せられない。",
      "season": 1,
      "year": 2024,
      "platform": "tv",
      "total_episodes": 14,
      "poster_url": "https://lain.bgm.tv/pic/cover/l/e8/b0/475367_8q8o8.jpg",
      "air_date": "2024-07-06",
      "air_week": 6
    },
    {
      "mikan_id": "3418",
      "bgmtv_id": 289854,
      "tmdb_id": null,
      "title_chinese": "漩涡",
      "title_japanese": "うずまき",
      "season": 1,
      "year": 2024,
      "platform": "tv",
      "total_episodes": 4,
      "poster_url": "https://lain.bgm.tv/pic/cover/l/12/51/289854_x58Kd.jpg",
      "air_date": "2024-09-28",
      "air_week": 6
    },
    {
      "mikan_id": "3386",
      "bgmtv_id": 397604,
      "tmdb_id": null,
      "title_chinese": "亚托莉 -我挚爱的时光-",
      "title_japanese": "ATRI -My Dear Moments-",
      "season": 1,
      "year": 2024,
      "platform": "tv",
      "total_episodes": 13,
      "poster_url": "https://lain.bgm.tv/pic/cover/l/66/6d/397604_TgJ63.jpg",
      "air_date": "2024-07-13",
      "air_week": 6
    },
    {
      "mikan_id": "3421",
      "bgmtv_id": 451119,
      "tmdb_id": null,
      "title_chinese": "重来吧、魔王大人！R",
      "title_japanese": "魔王様、リトライ！Ｒ",
      "season": 1,
      "year": 2024,
      "platform": "tv",
      "total_episodes": 12,
      "poster_url": "https://lain.bgm.tv/pic/cover/l/d5/41/451119_SbNnf.jpg",
      "air_date": "2024-10-05",
      "air_week": 6
    },
    {
      "mikan_id": "2708",
      "bgmtv_id": 362997,
      "tmdb_id": null,
      "title_chinese": "游戏王 Go Rush！！",
      "title_japanese": "遊☆戯☆王ゴーラッシュ!!",
      "season": 1,
      "year": 2022,
      "platform": "tv",
      "total_episodes": 151,
      "poster_url": "https://lain.bgm.tv/pic/cover/l/bd/00/362997_GMGCF.jpg",
      "air_date": "2022-04-03",
      "air_week": 0
    },
    {
      "mikan_id": "3274",
      "bgmtv_id": 467784,
      "tmdb_id": null,
      "title_chinese": "美妙宠物 光之美少女！",
      "title_japanese": "わんだふるぷりきゅあ！",
      "season": 1,
      "year": 2024,
      "platform": "tv",
      "total_episodes": 50,
      "poster_url": "https://lain.bgm.tv/pic/cover/l/17/62/467784_4422O.jpg",
      "air_date": "2024-02-04",
      "air_week": 0
    },
    {
      "mikan_id": "2980",
      "bgmtv_id": 413786,
      "tmdb_id": null,
      "title_chinese": "逃走中 GREAT MISSION",
      "title_japanese": "逃走中 グレートミッション",
      "season": 1,
      "year": 2023,
      "platform": "tv",
      "total_episodes": 98,
      "poster_url": "https://lain.bgm.tv/pic/cover/l/80/50/413786_1NqZt.jpg",
      "air_date": "2023-04-02",
      "air_week": 0
    },
    {
      "mikan_id": "3392",
      "bgmtv_id": 474906,
      "tmdb_id": null,
      "title_chinese": "小市民系列",
      "title_japanese": "小市民シリーズ",
      "season": 1,
      "year": 2024,
      "platform": "tv",
      "total_episodes": 10,
      "poster_url": "https://lain.bgm.tv/pic/cover/l/e2/f4/474906_z0h44.jpg",
      "air_date": "2024-07-06",
      "air_week": 6
    },
    {
      "mikan_id": "3402",
      "bgmtv_id": 485122,
      "tmdb_id": null,
      "title_chinese": "现代误译",
      "title_japanese": "現代誤訳",
      "season": 1,
      "year": 2024,
      "platform": "tv",
      "total_episodes": 24,
      "poster_url": "https://lain.bgm.tv/pic/cover/l/8c/e4/485122_37pLb.jpg",
      "air_date": "2024-07-06",
      "air_week": 6
    },
    {
      "mikan_id": "3398",
      "bgmtv_id": 440879,
      "tmdb_id": null,
      "title_chinese": "卡片战斗先导者 DivineZ",
      "title_japanese": "カードファイト!! ヴァンガード Divinez",
      "season": 2,
      "year": 2024,
      "platform": "tv",
      "total_episodes": 14,
      "poster_url": "https://lain.bgm.tv/pic/cover/l/e1/c0/440879_gC34F.jpg",
      "air_date": "2024-07-06",
      "air_week": 6
    },
    {
      "mikan_id": "3395",
      "bgmtv_id": 446175,
      "tmdb_id": null,
      "title_chinese": "魔导具师妲莉亚永不妥协",
      "title_japanese": "魔導具師ダリヤはうつむかない",
      "season": 1,
      "year": 2024,
      "platform": "tv",
      "total_episodes": 12,
      "poster_url": "https://lain.bgm.tv/pic/cover/l/46/7b/446175_kherQ.jpg",
      "air_date": "2024-07-06",
      "air_week": 6
    },
    {
      "mikan_id": "227",
      "bgmtv_id": 899,
      "tmdb_id": null,
      "title_chinese": "名侦探柯南",
      "title_japanese": "名探偵コナン",
      "season": 1,
      "year": 1996,
      "platform": "tv",
      "total_episodes": 1308,
      "poster_url": "https://lain.bgm.tv/pic/cover/l/01/88/899_REwVW.jpg",
      "air_date": "1996-01-08",
      "air_week": 0
    },
    {
      "mikan_id": "228",
      "bgmtv_id": 975,
      "tmdb_id": null,
      "title_chinese": "航海王",
      "title_japanese": "ONE PIECE",
      "season": 1,
      "year": 1999,
      "platform": "tv",
      "total_episodes": 1191,
      "poster_url": "https://lain.bgm.tv/pic/cover/l/92/97/975_YKuWd.jpg",
      "air_date": "1999-10-20",
      "air_week": 0
    },
    {
      "mikan_id": "3396",
      "bgmtv_id": 424573,
      "tmdb_id": null,
      "title_chinese": "擅长逃跑的殿下",
      "title_japanese": "逃げ上手の若君",
      "season": 1,
      "year": 2024,
      "platform": "tv",
      "total_episodes": 13,
      "poster_url": "https://lain.bgm.tv/pic/cover/l/32/14/424573_YYLzT.jpg",
      "air_date": "2024-07-06",
      "air_week": 6
    },
    {
      "mikan_id": "3399",
      "bgmtv_id": 349093,
      "tmdb_id": null,
      "title_chinese": "妖精的尾巴 百年任务",
      "title_japanese": "FAIRY TAIL 100年クエスト",
      "season": 1,
      "year": 2024,
      "platform": "tv",
      "total_episodes": 26,
      "poster_url": "https://lain.bgm.tv/pic/cover/l/e8/2c/349093_DJuws.jpg",
      "air_date": "2024-07-07",
      "air_week": 0
    },
    {
      "mikan_id": "3278",
      "bgmtv_id": 383251,
      "tmdb_id": null,
      "title_chinese": "忍者神威",
      "title_japanese": "Ninja Kamui",
      "season": 1,
      "year": 2024,
      "platform": "tv",
      "total_episodes": 13,
      "poster_url": "https://lain.bgm.tv/pic/cover/l/62/3b/383251_7BhzH.jpg",
      "air_date": "2024-02-10",
      "air_week": 0
    },
    {
      "mikan_id": "3400",
      "bgmtv_id": 394996,
      "tmdb_id": null,
      "title_chinese": "神之塔",
      "title_japanese": "神之塔 -Tower of God- 2nd Season",
      "season": 2,
      "year": 2024,
      "platform": "tv",
      "total_episodes": 26,
      "poster_url": "https://lain.bgm.tv/pic/cover/l/de/86/394996_p2P3w.jpg",
      "air_date": "2024-07-07",
      "air_week": 0
    },
    {
      "mikan_id": "3371",
      "bgmtv_id": 424853,
      "tmdb_id": null,
      "title_chinese": "金肉人 完美超人始祖篇",
      "title_japanese": "キン肉マン 完璧超人始祖編",
      "season": 1,
      "year": 2024,
      "platform": "tv",
      "total_episodes": 12,
      "poster_url": "https://lain.bgm.tv/pic/cover/l/1b/83/424853_J6II2.jpg",
      "air_date": "2024-07-07",
      "air_week": 0
    },
    {
      "mikan_id": "3378",
      "bgmtv_id": 467811,
      "tmdb_id": null,
      "title_chinese": "异世界悠闲纪行 ～边养娃边当冒险者～",
      "title_japanese": "異世界ゆるり紀行 ～子育てしながら冒険者します～",
      "season": 1,
      "year": 2024,
      "platform": "tv",
      "total_episodes": 12,
      "poster_url": "https://lain.bgm.tv/pic/cover/l/6c/36/467811_WRG0r.jpg",
      "air_date": "2024-07-07",
      "air_week": 0
    },
    {
      "mikan_id": "3304",
      "bgmtv_id": 411276,
      "tmdb_id": null,
      "title_chinese": "夜樱家的大作战",
      "title_japanese": "夜桜さんちの大作戦",
      "season": 1,
      "year": 2024,
      "platform": "tv",
      "total_episodes": 27,
      "poster_url": "https://lain.bgm.tv/pic/cover/l/9d/9a/411276_Kzyt0.jpg",
      "air_date": "2024-04-07",
      "air_week": 0
    },
    {
      "mikan_id": "3372",
      "bgmtv_id": 477207,
      "tmdb_id": null,
      "title_chinese": "深夜重拳",
      "title_japanese": "真夜中ぱんチ",
      "season": 1,
      "year": 2024,
      "platform": "tv",
      "total_episodes": 12,
      "poster_url": "https://lain.bgm.tv/pic/cover/l/0c/cf/477207_0lA1U.jpg",
      "air_date": "2024-07-08",
      "air_week": 0
    },
    {
      "mikan_id": "3367",
      "bgmtv_id": 484761,
      "tmdb_id": null,
      "title_chinese": "鹿乃子乃子乃子虎视眈眈",
      "title_japanese": "しかのこのこのここしたんたん",
      "season": 1,
      "year": 2024,
      "platform": "tv",
      "total_episodes": 12,
      "poster_url": "https://lain.bgm.tv/pic/cover/l/b1/7b/484761_r83E8.jpg",
      "air_date": "2024-07-07",
      "air_week": 0
    },
    {
      "mikan_id": "3388",
      "bgmtv_id": 464561,
      "tmdb_id": null,
      "title_chinese": "亦叶亦花",
      "title_japanese": "菜なれ花なれ",
      "season": 1,
      "year": 2024,
      "platform": "tv",
      "total_episodes": 12,
      "poster_url": "https://lain.bgm.tv/pic/cover/l/d5/89/464561_DRdV0.jpg",
      "air_date": "2024-07-07",
      "air_week": 0
    },
    {
      "mikan_id": "3381",
      "bgmtv_id": 416320,
      "tmdb_id": null,
      "title_chinese": "身为VTuber的我因为忘记关台而成了传说",
      "title_japanese": "VTuberなんだが配信切り忘れたら伝説になってた",
      "season": 1,
      "year": 2024,
      "platform": "tv",
      "total_episodes": 12,
      "poster_url": "https://lain.bgm.tv/pic/cover/l/fb/28/416320_Iprrq.jpg",
      "air_date": "2024-07-07",
      "air_week": 0
    },
    {
      "mikan_id": "3412",
      "bgmtv_id": 497620,
      "tmdb_id": null,
      "title_chinese": "0岁儿童开始冲刺的故事",
      "title_japanese": "0歳児スタートダッシュ物語",
      "season": 1,
      "year": 2024,
      "platform": "tv",
      "total_episodes": 12,
      "poster_url": "https://lain.bgm.tv/pic/cover/l/de/49/497620_JdDD9.jpg",
      "air_date": "2024-07-07",
      "air_week": 0
    },
    {
      "mikan_id": "3415",
      "bgmtv_id": 507433,
      "tmdb_id": null,
      "title_chinese": "监禁区域LevelX",
      "title_japanese": "監禁区域レベルX",
      "season": 1,
      "year": 2024,
      "platform": "tv",
      "total_episodes": 6,
      "poster_url": "https://lain.bgm.tv/pic/cover/l/b9/55/507433_00reD.jpg",
      "air_date": "2024-09-06",
      "air_week": 0
    },
    {
      "mikan_id": "3416",
      "bgmtv_id": 481410,
      "tmdb_id": null,
      "title_chinese": "叹气的亡灵想隐退",
      "title_japanese": "嘆きの亡霊は引退したい",
      "season": 1,
      "year": 2024,
      "platform": "tv",
      "total_episodes": 13,
      "poster_url": "https://lain.bgm.tv/pic/cover/l/76/9a/481410_f635f.jpg",
      "air_date": "2024-10-01",
      "air_week": 2
    },
    {
      "mikan_id": "3366",
      "bgmtv_id": 465884,
      "tmdb_id": null,
      "title_chinese": "魔法少女与邪恶曾经敌对。",
      "title_japanese": "かつて魔法少女と悪は敵対していた。",
      "season": 1,
      "year": 2024,
      "platform": "tv",
      "total_episodes": 12,
      "poster_url": "https://lain.bgm.tv/pic/cover/l/c9/4f/465884_fqZbB.jpg",
      "air_date": "2024-07-09",
      "air_week": 2
    },
    {
      "mikan_id": "3417",
      "bgmtv_id": 491151,
      "tmdb_id": null,
      "title_chinese": "依靠最弱辅助职能【话术士】的我统领世界最强氏族",
      "title_japanese": "最凶の支援職【話術士】である俺は世界最強クランを従える",
      "season": 1,
      "year": 2024,
      "platform": "tv",
      "total_episodes": 12,
      "poster_url": "https://lain.bgm.tv/pic/cover/l/e6/cb/491151_rNnm5.jpg",
      "air_date": "2024-10-07",
      "air_week": 1
    },
    {
      "mikan_id": "3361",
      "bgmtv_id": 477204,
      "tmdb_id": null,
      "title_chinese": "多数欠",
      "title_japanese": "多数欠",
      "season": 1,
      "year": 2024,
      "platform": "tv",
      "total_episodes": 24,
      "poster_url": "https://lain.bgm.tv/pic/cover/l/ed/d9/477204_BBEAh.jpg",
      "air_date": "2024-07-02",
      "air_week": 2
    },
    {
      "mikan_id": "3360",
      "bgmtv_id": 482776,
      "tmdb_id": null,
      "title_chinese": "我的妻子没有感情",
      "title_japanese": "僕の妻は感情がない",
      "season": 1,
      "year": 2024,
      "platform": "tv",
      "total_episodes": 12,
      "poster_url": "https://lain.bgm.tv/pic/cover/l/ce/50/482776_G98Y9.jpg",
      "air_date": "2024-07-02",
      "air_week": 2
    },
    {
      "mikan_id": "3330",
      "bgmtv_id": 372010,
      "tmdb_id": null,
      "title_chinese": "狼与香辛料 行商邂逅贤狼",
      "title_japanese": "狼と香辛料 MERCHANT MEETS THE WISE WOLF",
      "season": 1,
      "year": 2024,
      "platform": "tv",
      "total_episodes": 25,
      "poster_url": "https://lain.bgm.tv/pic/cover/l/08/df/372010_KBWk9.jpg",
      "air_date": "2024-04-01",
      "air_week": 1
    },
    {
      "mikan_id": "3404",
      "bgmtv_id": 479477,
      "tmdb_id": null,
      "title_chinese": "杖与剑的魔剑谭",
      "title_japanese": "杖と剣のウィストリア",
      "season": 1,
      "year": 2024,
      "platform": "tv",
      "total_episodes": 12,
      "poster_url": "https://lain.bgm.tv/pic/cover/l/6d/e5/479477_19844.jpg",
      "air_date": "2024-07-07",
      "air_week": 0
    },
    {
      "mikan_id": "3492",
      "bgmtv_id": 498178,
      "tmdb_id": null,
      "title_chinese": "暗芝居",
      "title_japanese": "闇芝居 十三期",
      "season": 1,
      "year": 2024,
      "platform": "tv",
      "total_episodes": 13,
      "poster_url": "https://lain.bgm.tv/pic/cover/l/1b/44/498178_MQq3q.jpg",
      "air_date": "2024-07-14",
      "air_week": 0
    },
    {
      "mikan_id": "3359",
      "bgmtv_id": 427059,
      "tmdb_id": null,
      "title_chinese": "大叔新人冒险者，被最强小队往死里锻炼后变无敌了",
      "title_japanese": "新米オッサン冒険者、最強パーティに死ぬほど鍛えられて無敵になる。",
      "season": 1,
      "year": 2024,
      "platform": "tv",
      "total_episodes": 12,
      "poster_url": "https://lain.bgm.tv/pic/cover/l/6a/45/427059_1V5vV.jpg",
      "air_date": "2024-07-01",
      "air_week": 1
    },
    {
      "mikan_id": "3403",
      "bgmtv_id": 488197,
      "tmdb_id": null,
      "title_chinese": "战国妖狐 千魔混沌篇",
      "title_japanese": "戦国妖狐 千魔混沌編",
      "season": 1,
      "year": 2024,
      "platform": "tv",
      "total_episodes": 25,
      "poster_url": "https://lain.bgm.tv/pic/cover/l/15/67/488197_934y5.jpg",
      "air_date": "2024-07-17",
      "air_week": 3
    },
    {
      "mikan_id": "3383",
      "bgmtv_id": 351349,
      "tmdb_id": null,
      "title_chinese": "你与我最后的战场，亦或是世界起始的圣战",
      "title_japanese": "キミと僕の最後の戦場、あるいは世界が始まる聖戦 Season II",
      "season": 2,
      "year": 2024,
      "platform": "tv",
      "total_episodes": 12,
      "poster_url": "https://lain.bgm.tv/pic/cover/l/e5/fc/351349_Z8mpG.jpg",
      "air_date": "2024-07-10",
      "air_week": 3
    },
    {
      "mikan_id": "3393",
      "bgmtv_id": 470874,
      "tmdb_id": null,
      "title_chinese": "腼腆英雄 东京夺还篇",
      "title_japanese": "SHY 東京奪還編",
      "season": 1,
      "year": 2024,
      "platform": "tv",
      "total_episodes": 12,
      "poster_url": "https://lain.bgm.tv/pic/cover/l/cd/89/470874_zSyEG.jpg",
      "air_date": "2024-07-01",
      "air_week": 1
    },
    {
      "mikan_id": "3411",
      "bgmtv_id": 448879,
      "tmdb_id": null,
      "title_chinese": "德里科的托儿所",
      "title_japanese": "デリコズ・ナーサリー",
      "season": 1,
      "year": 2024,
      "platform": "tv",
      "total_episodes": 13,
      "poster_url": "https://lain.bgm.tv/pic/cover/l/b7/15/448879_b6Jb9.jpg",
      "air_date": "2024-08-07",
      "air_week": 3
    },
    {
      "mikan_id": "3401",
      "bgmtv_id": 490824,
      "tmdb_id": null,
      "title_chinese": "哎咕岛消失的舔甜歌姬",
      "title_japanese": "エグミレガシー",
      "season": 1,
      "year": 2024,
      "platform": "tv",
      "total_episodes": 12,
      "poster_url": "https://lain.bgm.tv/pic/cover/l/9f/21/490824_8oJpo.jpg",
      "air_date": "2024-07-09",
      "air_week": 2
    },
    {
      "mikan_id": "3354",
      "bgmtv_id": 475933,
      "tmdb_id": null,
      "title_chinese": "魔王军最强的魔术师是人类",
      "title_japanese": "魔王軍最強の魔術師は人間だった",
      "season": 1,
      "year": 2024,
      "platform": "tv",
      "total_episodes": 12,
      "poster_url": "https://lain.bgm.tv/pic/cover/l/0b/e5/475933_Kf14e.jpg",
      "air_date": "2024-07-03",
      "air_week": 3
    },
    {
      "mikan_id": "3382",
      "bgmtv_id": 445722,
      "tmdb_id": null,
      "title_chinese": "恋爱没法用双子除尽",
      "title_japanese": "恋は双子で割り切れない",
      "season": 1,
      "year": 2024,
      "platform": "tv",
      "total_episodes": 12,
      "poster_url": "https://lain.bgm.tv/pic/cover/l/88/cd/445722_8A9Gy.jpg",
      "air_date": "2024-07-10",
      "air_week": 3
    },
    {
      "mikan_id": "3373",
      "bgmtv_id": 424883,
      "tmdb_id": null,
      "title_chinese": "不时轻声地以俄语遮羞的邻座艾莉同学",
      "title_japanese": "時々ボソッとロシア語でデレる隣のアーリャさん",
      "season": 1,
      "year": 2024,
      "platform": "tv",
      "total_episodes": 12,
      "poster_url": "https://lain.bgm.tv/pic/cover/l/7c/8e/424883_5X5X2.jpg",
      "air_date": "2024-07-03",
      "air_week": 3
    },
    {
      "mikan_id": "3148",
      "bgmtv_id": 412164,
      "tmdb_id": null,
      "title_chinese": "放学后少年花子君",
      "title_japanese": "放課後少年花子くん",
      "season": 1,
      "year": 2023,
      "platform": "tv",
      "total_episodes": 4,
      "poster_url": "https://lain.bgm.tv/pic/cover/l/c2/22/412164_Rbz3C.jpg",
      "air_date": "2023-10-12",
      "air_week": 4
    },
    {
      "mikan_id": "3379",
      "bgmtv_id": 391496,
      "tmdb_id": null,
      "title_chinese": "异世界失格",
      "title_japanese": "異世界失格",
      "season": 1,
      "year": 2024,
      "platform": "tv",
      "total_episodes": 12,
      "poster_url": "https://lain.bgm.tv/pic/cover/l/51/3f/391496_5G4nn.jpg",
      "air_date": "2024-07-09",
      "air_week": 2
    },
    {
      "mikan_id": "3368",
      "bgmtv_id": 463389,
      "tmdb_id": null,
      "title_chinese": "我要招架一切 逆向误解的世界最强梦想成为冒险者",
      "title_japanese": "俺は全てを【パリイ】する〜逆勘違いの世界最強は冒険者になりたい〜",
      "season": 1,
      "year": 2024,
      "platform": "tv",
      "total_episodes": 12,
      "poster_url": "https://lain.bgm.tv/pic/cover/l/c7/57/463389_PGZ0p.jpg",
      "air_date": "2024-07-04",
      "air_week": 4
    },
    {
      "mikan_id": "3375",
      "bgmtv_id": 467243,
      "tmdb_id": null,
      "title_chinese": "拉面赤猫",
      "title_japanese": "ラーメン赤猫",
      "season": 1,
      "year": 2024,
      "platform": "tv",
      "total_episodes": 12,
      "poster_url": "https://lain.bgm.tv/pic/cover/l/60/b2/467243_hB6fN.jpg",
      "air_date": "2024-07-04",
      "air_week": 4
    },
    {
      "mikan_id": "3407",
      "bgmtv_id": 443428,
      "tmdb_id": null,
      "title_chinese": "【我推的孩子】",
      "title_japanese": "【推しの子】",
      "season": 2,
      "year": 2024,
      "platform": "tv",
      "total_episodes": 14,
      "poster_url": "https://lain.bgm.tv/pic/cover/l/d1/1c/443428_FIhFu.jpg",
      "air_date": "2024-07-03",
      "air_week": 3
    },
    {
      "mikan_id": "3387",
      "bgmtv_id": 393037,
      "tmdb_id": null,
      "title_chinese": "义妹生活",
      "title_japanese": "義妹生活",
      "season": 1,
      "year": 2024,
      "platform": "tv",
      "total_episodes": 12,
      "poster_url": "https://lain.bgm.tv/pic/cover/l/40/01/393037_I7mvN.jpg",
      "air_date": "2024-07-04",
      "air_week": 4
    },
    {
      "mikan_id": "3384",
      "bgmtv_id": 443931,
      "tmdb_id": null,
      "title_chinese": "黄昏光影",
      "title_japanese": "黄昏アウトフォーカス",
      "season": 1,
      "year": 2024,
      "platform": "tv",
      "total_episodes": 12,
      "poster_url": "https://lain.bgm.tv/pic/cover/l/75/82/443931_E6OC7.jpg",
      "air_date": "2024-07-04",
      "air_week": 4
    },
    {
      "mikan_id": "3389",
      "bgmtv_id": 425988,
      "tmdb_id": null,
      "title_chinese": "前辈是男孩子",
      "title_japanese": "先輩はおとこのこ",
      "season": 1,
      "year": 2024,
      "platform": "tv",
      "total_episodes": 12,
      "poster_url": "https://lain.bgm.tv/pic/cover/l/53/76/425988_RH9UK.jpg",
      "air_date": "2024-07-04",
      "air_week": 4
    },
    {
      "mikan_id": "3414",
      "bgmtv_id": 476129,
      "tmdb_id": null,
      "title_chinese": "独自一人的异世界攻略",
      "title_japanese": "ひとりぼっちの異世界攻略",
      "season": 1,
      "year": 2024,
      "platform": "tv",
      "total_episodes": 12,
      "poster_url": "https://lain.bgm.tv/pic/cover/l/d2/66/476129_q83DE.jpg",
      "air_date": "2024-10-03",
      "air_week": 4
    },
    {
      "mikan_id": "3390",
      "bgmtv_id": 428823,
      "tmdb_id": null,
      "title_chinese": "疑似后宫",
      "title_japanese": "疑似ハーレム",
      "season": 1,
      "year": 2024,
      "platform": "tv",
      "total_episodes": 12,
      "poster_url": "https://lain.bgm.tv/pic/cover/l/0c/fd/428823_vuwNR.jpg",
      "air_date": "2024-07-04",
      "air_week": 4
    },
    {
      "mikan_id": "3405",
      "bgmtv_id": 476418,
      "tmdb_id": null,
      "title_chinese": "依靠被嫌弃的【状态异常技能】而成为最强的我最终蹂躏一切",
      "title_japanese": "ハズレ枠の【状態異常スキル】で最強になった俺がすべてを蹂躙するまで",
      "season": 1,
      "year": 2024,
      "platform": "tv",
      "total_episodes": 13,
      "poster_url": "https://lain.bgm.tv/pic/cover/l/ac/c5/476418_50C5z.jpg",
      "air_date": "2024-07-04",
      "air_week": 4
    },
    {
      "mikan_id": "3409",
      "bgmtv_id": 442673,
      "tmdb_id": null,
      "title_chinese": "女神咖啡厅",
      "title_japanese": "女神のカフェテラス",
      "season": 2,
      "year": 2024,
      "platform": "tv",
      "total_episodes": 12,
      "poster_url": "https://lain.bgm.tv/pic/cover/l/19/d2/442673_23MtT.jpg",
      "air_date": "2024-07-04",
      "air_week": 4
    }
  ]
}
